cryze_server/__init__.py
cryze_server/run_server.py
cryze_server/server.py
cryze_server-0.0.18.dist-info/LICENSE
cryze_server-0.0.18.dist-info/METADATA
cryze_server-0.0.18.dist-info/WHEEL
cryze_server-0.0.18.dist-info/entry_points.txt
cryze_server-0.0.18.dist-info/top_level.txt
cryze_server-0.0.18.dist-info/RECORD
